opsbeacon/__init__.py
opsbeacon/opsbeacon.py
opsbeacon-1.2.3.dist-info/licenses/LICENSE
opsbeacon-1.2.3.dist-info/METADATA
opsbeacon-1.2.3.dist-info/WHEEL
opsbeacon-1.2.3.dist-info/top_level.txt
opsbeacon-1.2.3.dist-info/RECORD
