Metadata-Version: 2.4
Name: opsbeacon
Version: 1.2.3
Summary: OpsBeacon python client library to interact with the OpsBeacon API
Home-page: https://github.com/ob2ai/ob-python-sdk
Author: Cihan Sahin
Author-email: cihan@opsbeacon.com
Classifier: Programming Language :: Python :: 3
Classifier: License :: OSI Approved :: MIT License
Classifier: Operating System :: OS Independent
Requires-Python: >=3.8
License-File: LICENSE
Requires-Dist: requests>=2.25.1
Provides-Extra: cli
Requires-Dist: python-dotenv>=1.1.0; extra == "cli"
Dynamic: author
Dynamic: author-email
Dynamic: classifier
Dynamic: description
Dynamic: description-content-type
Dynamic: home-page
Dynamic: license-file
Dynamic: provides-extra
Dynamic: requires-dist
Dynamic: requires-python
Dynamic: summary
